ster_py-2.0.1.dist-info/DESCRIPTION.rst
ster_py-2.0.1.dist-info/METADATA
ster_py-2.0.1.dist-info/RECORD
ster_py-2.0.1.dist-info/WHEEL
ster_py-2.0.1.dist-info/entry_points.txt
ster_py-2.0.1.dist-info/metadata.json
ster_py-2.0.1.dist-info/top_level.txt
sterpy/__init__.py
sterpy/sterpy.py
