Metadata-Version: 2.0
Name: ster-py
Version: 2.0.1
Summary: A python cli based sterkinekor browser, whatever, it needed to be done.
Home-page: https://github.com/spookyUnknownUser/ster-py
Author: spookyUnknownUser
Author-email: spookyUnknownUser@users.noreply.github.com
License: MIT
Keywords: cli command python sterkinekor browser
Platform: UNKNOWN
Classifier: Development Status :: 3 - Alpha
Classifier: Intended Audience :: Developers
Classifier: Topic :: Utilities
Classifier: License :: OSI Approved :: MIT License
Classifier: Programming Language :: Python :: 2.7
Requires-Dist: click
Requires-Dist: colorama
Requires-Dist: omdb
Requires-Dist: requests
